{
    "_default": {
        "9": {
            "git_branch": "master",
            "git_commit": "HEAD",
            "git_last_commit": "c1b2131c6df1ddf5438d8829f086ed5f1dfca38d",
            "git_last_date": "180210.015211",
            "name": "elementary-icon-theme",
            "package_name": "elementary-icon-theme",
            "package_version": "4.3.1",
            "rpm_last_release": "1%{?dist}",
            "rpm_last_version": "4.3.1+git%{date}.%{commit}"
        },
        "10": {
            "git_branch": "master",
            "git_commit": "HEAD",
            "git_last_commit": "e496c542e9057c93821b0455db685ee726c399c7",
            "git_last_date": "180210.174550",
            "name": "elementary-theme",
            "package_name": "elementary-theme",
            "package_version": "5.1.1",
            "rpm_last_release": "1%{?dist}",
            "rpm_last_version": "5.1.1+git%{date}.%{commit}"
        },
        "57": {
            "git_branch": "master",
            "git_commit": "HEAD",
            "git_last_commit": "ffa8cd07fd00178577097bdfb184b1d030d1ae36",
            "git_last_date": "180211.000840",
            "name": "switchboard-plug-pantheon-shell",
            "package_name": "switchboard-plug-pantheon-shell",
            "package_version": "0.2.6",
            "rpm_last_release": "1%{?dist}",
            "rpm_last_version": "0.2.6+git%{date}.%{commit}"
        },
        "59": {
            "git_branch": "master",
            "git_commit": "HEAD",
            "git_last_commit": "20b9f801c74e8d4eb8a9edfb90b2349207445187",
            "git_last_date": "171111.195157",
            "name": "gsignond",
            "package_name": "gsignond",
            "package_version": "1.0.6",
            "rpm_last_release": "1%{?dist}",
            "rpm_last_version": "1.0.6+git%{date}.%{commit}"
        },
        "60": {
            "git_branch": "master",
            "git_commit": "HEAD",
            "git_last_commit": "5e9c8f71bd523cfb397191230b977b373f903991",
            "git_last_date": "171115.093207",
            "name": "libgsignon-glib",
            "package_name": "libgsignon-glib",
            "package_version": "2.4.1",
            "rpm_last_release": "1%{?dist}",
            "rpm_last_version": "2.4.1+git%{date}.%{commit}"
        },
        "61": {
            "git_branch": "master",
            "git_commit": "HEAD",
            "git_last_commit": "3b2f0c2a28b1c2e4d6b964e30a3ce78f30209ce3",
            "git_last_date": "180212.000422",
            "name": "pantheon-mail",
            "package_name": "pantheon-mail",
            "package_version": "1.0.6",
            "rpm_last_release": "1%{?dist}",
            "rpm_last_version": "1.0.6+git%{date}.%{commit}"
        },
        "62": {
            "git_branch": "master",
            "git_commit": "HEAD",
            "git_last_commit": "5414fb9478bfad3c45be4ede7741540edf74c6a9",
            "git_last_date": "180211.000811",
            "name": "pantheon-agent-geoclue2",
            "package_name": "pantheon-agent-geoclue2",
            "package_version": "0",
            "rpm_last_release": "1%{?dist}",
            "rpm_last_version": "0+git%{date}.%{commit}"
        },
        "63": {
            "git_branch": "master",
            "git_commit": "HEAD",
            "git_last_commit": "86f9a2b376d17696085d71073a3191475030d4f6",
            "git_last_date": "180211.000918",
            "name": "switchboard-plug-onlineaccounts",
            "package_name": "switchboard-plug-onlineaccounts",
            "package_version": "0.3.0.1",
            "rpm_last_release": "1%{?dist}",
            "rpm_last_version": "0.3.0.1+git%{date}.%{commit}"
        },
        "64": {
            "git_branch": "master",
            "git_commit": "HEAD",
            "git_last_commit": "f2f49553cdaf9a6b09bf97e9edcb12b69eb17808",
            "git_last_date": "180206.201107",
            "name": "capnet-assist",
            "package_name": "capnet-assist",
            "package_version": "0.2.1",
            "rpm_last_release": "1%{?dist}",
            "rpm_last_version": "0.2.1+git%{date}.%{commit}"
        },
        "66": {
            "git_branch": "master",
            "git_commit": "HEAD",
            "git_last_commit": "88009646255d776e1222d8a8f0d94478c7fc098e",
            "git_last_date": "180209.001231",
            "name": "wingpanel-indicator-sound",
            "package_name": "wingpanel-indicator-sound",
            "package_version": "2.0.5",
            "rpm_last_release": "1%{?dist}",
            "rpm_last_version": "2.0.5+git%{date}.%{commit}"
        },
        "67": {
            "git_branch": "master",
            "git_commit": "HEAD",
            "git_last_commit": "93d233a4cc64297c53388c9daf3d87358ff16cbf",
            "git_last_date": "180211.000915",
            "name": "switchboard-plug-datetime",
            "package_name": "switchboard-plug-datetime",
            "package_version": "0.1.2",
            "rpm_last_release": "1%{?dist}",
            "rpm_last_version": "0.1.2+git%{date}.%{commit}"
        },
        "68": {
            "git_branch": "master",
            "git_commit": "HEAD",
            "git_last_commit": "53f094bc1b5c8e27c18971006ab7e5e9ec5da869",
            "git_last_date": "180204.211214",
            "name": "wingpanel-indicator-power",
            "package_name": "wingpanel-indicator-power",
            "package_version": "2.1.1",
            "rpm_last_release": "1%{?dist}",
            "rpm_last_version": "2.1.1+git%{date}.%{commit}"
        },
        "69": {
            "git_branch": "master",
            "git_commit": "HEAD",
            "git_last_commit": "6445598eff8bc4d1618b7b3443a7b976d2da4439",
            "git_last_date": "180207.033038",
            "name": "switchboard-plug-display",
            "package_name": "switchboard-plug-display",
            "package_version": "0.1.3",
            "rpm_last_release": "1%{?dist}",
            "rpm_last_version": "0.1.3+git%{date}.%{commit}"
        },
        "70": {
            "git_branch": "master",
            "git_commit": "HEAD",
            "git_last_commit": "638fdf84eeecf6c00478e7409375a69bb72d4e48",
            "git_last_date": "180211.001110",
            "name": "wingpanel-indicator-keyboard",
            "package_name": "wingpanel-indicator-keyboard",
            "package_version": "2.0.2",
            "rpm_last_release": "1%{?dist}",
            "rpm_last_version": "2.0.2+git%{date}.%{commit}"
        },
        "72": {
            "git_branch": "master",
            "git_commit": "HEAD",
            "git_last_commit": "19cbaf092ff08249780b9cdc42568560dd204850",
            "git_last_date": "180211.175919",
            "name": "granite",
            "package_name": "granite",
            "package_version": "0.5",
            "rpm_last_release": "1%{?dist}",
            "rpm_last_version": "0.5+git%{date}.%{commit}"
        },
        "73": {
            "git_branch": "master",
            "git_commit": "HEAD",
            "git_last_commit": "912e36f81e325ebac28b97a4d69f0cdaa1e4d4c3",
            "git_last_date": "180209.001034",
            "name": "switchboard-plug-a11y",
            "package_name": "switchboard-plug-a11y",
            "package_version": "0.1.1",
            "rpm_last_release": "1%{?dist}",
            "rpm_last_version": "0.1.1+git%{date}.%{commit}"
        },
        "74": {
            "git_branch": "master",
            "git_commit": "HEAD",
            "git_last_commit": "c1559f367c5ee69adc0e51cd39a002142deadefc",
            "git_last_date": "180211.000903",
            "name": "switchboard-plug-power",
            "package_name": "switchboard-plug-power",
            "package_version": "0.3.2",
            "rpm_last_release": "1%{?dist}",
            "rpm_last_version": "0.3.2+git%{date}.%{commit}"
        },
        "75": {
            "git_branch": "master",
            "git_commit": "HEAD",
            "git_last_commit": "1e7698695b165d550cd1fc91bf8724a21d3a0588",
            "git_last_date": "180211.000847",
            "name": "switchboard-plug-locale",
            "package_name": "switchboard-plug-locale",
            "package_version": "0.2.3",
            "rpm_last_release": "1%{?dist}",
            "rpm_last_version": "0.2.3+git%{date}.%{commit}"
        },
        "76": {
            "git_branch": "master",
            "git_commit": "HEAD",
            "git_last_commit": "baff339b841afb15bb7de3f514056c5bf2775d7a",
            "git_last_date": "180211.000810",
            "name": "slingshot-launcher",
            "package_name": "slingshot-launcher",
            "package_version": "2.2.0",
            "rpm_last_release": "1%{?dist}",
            "rpm_last_version": "2.2.0+git%{date}.%{commit}"
        },
        "77": {
            "git_branch": "master",
            "git_commit": "HEAD",
            "git_last_commit": "358f5cfafc0937d0b5c5f4b07326eb2227d834d8",
            "git_last_date": "180212.000337",
            "name": "appcenter",
            "package_name": "appcenter",
            "package_version": "0.2.6",
            "rpm_last_release": "1%{?dist}",
            "rpm_last_version": "0.2.6+git%{date}.%{commit}"
        },
        "78": {
            "git_branch": "master",
            "git_commit": "HEAD",
            "git_last_commit": "f278ea11a15d83bf30e6c512b9f015e71919b2db",
            "git_last_date": "180206.202826",
            "name": "wingpanel-indicator-notifications",
            "package_name": "wingpanel-indicator-notifications",
            "package_version": "2.0.2",
            "rpm_last_release": "1%{?dist}",
            "rpm_last_version": "2.0.2+git%{date}.%{commit}"
        },
        "79": {
            "git_branch": "master",
            "git_commit": "HEAD",
            "git_last_commit": "e72053a8d07e141a226951dcbabf64361317066c",
            "git_last_date": "180211.000746",
            "name": "switchboard-plug-useraccounts",
            "package_name": "switchboard-plug-useraccounts",
            "package_version": "0.1.6",
            "rpm_last_release": "1%{?dist}",
            "rpm_last_version": "0.1.6+git%{date}.%{commit}"
        },
        "80": {
            "git_branch": "master",
            "git_commit": "HEAD",
            "git_last_commit": "63c872fe4fb44a3e61cbcc0c448a5fde49b9d0c9",
            "git_last_date": "180103.001654",
            "name": "wingpanel-indicator-bluetooth",
            "package_name": "wingpanel-indicator-bluetooth",
            "package_version": "2.0.3",
            "rpm_last_release": "2%{?dist}",
            "rpm_last_version": "2.0.3+git%{date}.%{commit}"
        },
        "81": {
            "git_branch": "master",
            "git_commit": "HEAD",
            "git_last_commit": "afde90c39b9809a97401e5c466b5fe616817e1c3",
            "git_last_date": "180211.000856",
            "name": "switchboard-plug-notifications",
            "package_name": "switchboard-plug-notifications",
            "package_version": "0.1.2",
            "rpm_last_release": "1%{?dist}",
            "rpm_last_version": "0.1.2+git%{date}.%{commit}"
        },
        "82": {
            "git_branch": "master",
            "git_commit": "HEAD",
            "git_last_commit": "f324e542b6531306ffc11fff5b59316360c2a960",
            "git_last_date": "170703.192035",
            "name": "wingpanel-indicator-ayatana",
            "package_name": "wingpanel-indicator-ayatana",
            "package_version": "2.0.3",
            "rpm_last_release": "2%{?dist}",
            "rpm_last_version": "2.0.3+git%{date}.%{commit}"
        },
        "83": {
            "git_branch": "master",
            "git_commit": "HEAD",
            "git_last_commit": "6cddf0397249cdb6f3ba31c906e9364e151956e8",
            "git_last_date": "171218.142522",
            "name": "pantheon-agent-polkit",
            "package_name": "pantheon-agent-polkit",
            "package_version": "0.1.4",
            "rpm_last_release": "2%{?dist}",
            "rpm_last_version": "0.1.4+git%{date}.%{commit}"
        },
        "84": {
            "git_branch": "master",
            "git_commit": "HEAD",
            "git_last_commit": "24e4bc4a37659fd353f2420ca0e682ad97f91bd4",
            "git_last_date": "180123.164118",
            "name": "wingpanel",
            "package_name": "wingpanel",
            "package_version": "2.0.4",
            "rpm_last_release": "1%{?dist}",
            "rpm_last_version": "2.0.4+git%{date}.%{commit}"
        },
        "85": {
            "git_branch": "master",
            "git_commit": "HEAD",
            "git_last_commit": "c4abed557de47ec42715682c3ac642f106dd14e9",
            "git_last_date": "180211.001121",
            "name": "wingpanel-indicator-session",
            "package_name": "wingpanel-indicator-session",
            "package_version": "2.0.4",
            "rpm_last_release": "1%{?dist}",
            "rpm_last_version": "2.0.4+git%{date}.%{commit}"
        },
        "86": {
            "git_branch": "master",
            "git_commit": "HEAD",
            "git_last_commit": "bfeaae756ae2f7e191c84e61cf42d9528ada7641",
            "git_last_date": "180209.001219",
            "name": "wingpanel-indicator-datetime",
            "package_name": "wingpanel-indicator-datetime",
            "package_version": "2.0.2",
            "rpm_last_release": "1%{?dist}",
            "rpm_last_version": "2.0.2+git%{date}.%{commit}"
        },
        "87": {
            "git_branch": "master",
            "git_commit": "HEAD",
            "git_last_commit": "a1810189084200a2debe531c39e8717a04853b77",
            "git_last_date": "180211.000924",
            "name": "switchboard-plug-sound",
            "package_name": "switchboard-plug-sound",
            "package_version": "0",
            "rpm_last_release": "1%{?dist}",
            "rpm_last_version": "0+git%{date}.%{commit}"
        },
        "88": {
            "git_branch": "master",
            "git_commit": "HEAD",
            "git_last_commit": "271d4514b4839671fb58e944d3394af89b0710a6",
            "git_last_date": "180211.000907",
            "name": "switchboard-plug-printers",
            "package_name": "switchboard-plug-printers",
            "package_version": "0.1.2",
            "rpm_last_release": "1%{?dist}",
            "rpm_last_version": "0.1.2+git%{date}.%{commit}"
        },
        "89": {
            "git_branch": "master",
            "git_commit": "HEAD",
            "git_last_commit": "e32403acd15036e58f47ded04a00f462a2565b84",
            "git_last_date": "180209.001017",
            "name": "switchboard",
            "package_name": "switchboard",
            "package_version": "2.3.0",
            "rpm_last_release": "1%{?dist}",
            "rpm_last_version": "2.3.0+git%{date}.%{commit}"
        },
        "91": {
            "git_branch": "master",
            "git_commit": "HEAD",
            "git_last_commit": "feea6ddc990ba8c7e95e34e8bcfa12f3998477c2",
            "git_last_date": "180118.154753",
            "name": "audience",
            "package_name": "audience",
            "package_version": "0.2.4",
            "rpm_last_release": "1%{?dist}",
            "rpm_last_version": "0.2.4+git%{date}.%{commit}"
        },
        "93": {
            "git_branch": "master",
            "git_commit": "HEAD",
            "git_last_commit": "c0eb426f817e184c811a76f2acb8063361bda501",
            "git_last_date": "180130.135930",
            "name": "gala",
            "package_name": "gala",
            "package_version": "0.3.0",
            "rpm_last_release": "1%{?dist}",
            "rpm_last_version": "0.3.0+git%{date}.%{commit}"
        },
        "94": {
            "git_branch": "master",
            "git_commit": "HEAD",
            "git_last_commit": "f5508b151214c5ebbd81063c1d62e4a69fd79170",
            "git_last_date": "180209.004947",
            "name": "pantheon-greeter",
            "package_name": "pantheon-greeter",
            "package_version": "3.2.0",
            "rpm_last_release": "1%{?dist}",
            "rpm_last_version": "3.2.0+git%{date}.%{commit}"
        },
        "95": {
            "git_branch": "master",
            "git_commit": "HEAD",
            "git_last_commit": "1960ed8d33611896c416ec1ed7eaa6f5d2323735",
            "git_last_date": "180207.034654",
            "name": "wingpanel-indicator-network",
            "package_name": "wingpanel-indicator-network",
            "package_version": "2.1.1",
            "rpm_last_release": "1%{?dist}",
            "rpm_last_version": "2.1.1+git%{date}.%{commit}"
        },
        "96": {
            "git_branch": "master",
            "git_commit": "HEAD",
            "git_last_commit": "f2dfaec00f3786212af400d2ec6b38cc0c6c2247",
            "git_last_date": "180211.000853",
            "name": "switchboard-plug-networking",
            "package_name": "switchboard-plug-networking",
            "package_version": "0.1.1",
            "rpm_last_release": "1%{?dist}",
            "rpm_last_version": "0.1.1+git%{date}.%{commit}"
        },
        "97": {
            "git_branch": "master",
            "git_commit": "HEAD",
            "git_last_commit": "a8dc4447560c30788b816b396f66e900225e86c3",
            "git_last_date": "180209.001012",
            "name": "switchboard-plug-applications",
            "package_name": "switchboard-plug-applications",
            "package_version": "0.1.2",
            "rpm_last_release": "1%{?dist}",
            "rpm_last_version": "0.1.2+git%{date}.%{commit}"
        },
        "98": {
            "git_branch": "master",
            "git_commit": "HEAD",
            "git_last_commit": "ac859ebd7396291c6f305049acf8f183631b8145",
            "git_last_date": "180211.000844",
            "name": "switchboard-plug-keyboard",
            "package_name": "switchboard-plug-keyboard",
            "package_version": "0.3.2",
            "rpm_last_release": "1%{?dist}",
            "rpm_last_version": "0.3.2+git%{date}.%{commit}"
        },
        "99": {
            "git_branch": "master",
            "git_commit": "HEAD",
            "git_last_commit": "8c6d001970c49d5abe7752334c34cd6aafbaf1bc",
            "git_last_date": "180211.000850",
            "name": "switchboard-plug-mouse-touchpad",
            "package_name": "switchboard-plug-mouse-touchpad",
            "package_version": "0.1.2",
            "rpm_last_release": "1%{?dist}",
            "rpm_last_version": "0.1.2+git%{date}.%{commit}"
        },
        "100": {
            "git_branch": "master",
            "git_commit": "HEAD",
            "git_last_commit": "d5bd5de54604a8ec2bad82c04dbe540eff410fb6",
            "git_last_date": "180211.000859",
            "name": "switchboard-plug-parental-controls",
            "package_name": "switchboard-plug-parental-controls",
            "package_version": "0.1.3",
            "rpm_last_release": "1%{?dist}",
            "rpm_last_version": "0.1.3+git%{date}.%{commit}"
        },
        "101": {
            "git_branch": "master",
            "git_commit": "HEAD",
            "git_last_commit": "1140debeba686da1eeb1161064f246e94ddeb52e",
            "git_last_date": "180211.000921",
            "name": "switchboard-plug-sharing",
            "package_name": "switchboard-plug-sharing",
            "package_version": "0.1.1",
            "rpm_last_release": "1%{?dist}",
            "rpm_last_version": "0.1.1+git%{date}.%{commit}"
        },
        "102": {
            "git_branch": "master",
            "git_commit": "HEAD",
            "git_last_commit": "ca7bcfa5ec9197d3e23c2b37454e9c801b81b5d2",
            "git_last_date": "180212.074842",
            "name": "plank",
            "package_name": "plank",
            "package_version": "0.11.4",
            "rpm_last_release": "1%{?dist}",
            "rpm_last_version": "0.11.4+git%{date}.%{commit}"
        },
        "103": {
            "git_branch": "master",
            "git_commit": "HEAD",
            "git_last_commit": "319ec5336e9f05f3f22b886cc2053ef3d4b6599e",
            "git_last_date": "171229.154934",
            "name": "cmake-elementary",
            "package_name": "cmake-elementary",
            "package_version": "0.1.0",
            "rpm_last_release": "2%{?dist}",
            "rpm_last_version": "0.1.0+git%{date}.%{commit}"
        },
        "104": {
            "git_branch": "master",
            "git_commit": "HEAD",
            "git_last_commit": "5464ea09d42a0a62f1ac3a425d90280a9ed7f46d",
            "git_last_date": "170917.092344",
            "name": "mock-elementary-nightly",
            "package_name": "mock-elementary-nightly",
            "package_version": "0",
            "rpm_last_release": "1%{?dist}",
            "rpm_last_version": "0+git%{date}.%{commit}"
        },
        "105": {
            "git_branch": "master",
            "git_commit": "HEAD",
            "git_last_commit": "c1aebde100fd9fb42026b1ba186e6b9cb6380b3b",
            "git_last_date": "180205.001051",
            "name": "elementary-camera",
            "package_name": "elementary-camera",
            "package_version": "0.3.0.1",
            "rpm_last_release": "1%{?dist}",
            "rpm_last_version": "0.3.0.1+git%{date}.%{commit}"
        },
        "106": {
            "git_branch": "master",
            "git_commit": "HEAD",
            "git_last_commit": "30277f408eaf26683df9f0f71d8feda6743de698",
            "git_last_date": "180103.145139",
            "name": "vocal",
            "package_name": "vocal",
            "package_version": "2.1.5",
            "rpm_last_release": "2%{?dist}",
            "rpm_last_version": "2.1.5+git%{date}.%{commit}"
        },
        "107": {
            "git_branch": "master",
            "git_commit": "HEAD",
            "git_last_commit": "b36060b7b384c8f86d3fba153d7b2b645287df3b",
            "git_last_date": "171111.202603",
            "name": "gsignond-plugin-oauth",
            "package_name": "gsignond-plugin-oauth",
            "package_version": "0",
            "rpm_last_release": "1%{?dist}",
            "rpm_last_version": "0+git%{date}.%{commit}"
        },
        "108": {
            "git_branch": "master",
            "git_commit": "HEAD",
            "git_last_commit": "671022f3d941509d64249d8f887f4cb60f2a5aab",
            "git_last_date": "171111.210640",
            "name": "gsignond-plugin-sasl",
            "package_name": "gsignond-plugin-sasl",
            "package_version": "0",
            "rpm_last_release": "1%{?dist}",
            "rpm_last_version": "0+git%{date}.%{commit}"
        },
        "109": {
            "git_branch": "master",
            "git_commit": "HEAD",
            "git_last_commit": "de9123ea2e3245900b2711e9d95ee134b5cbfccb",
            "git_last_date": "180205.001138",
            "name": "switchboard-plug-about",
            "package_name": "switchboard-plug-about",
            "package_version": "0.2.4",
            "rpm_last_release": "1%{?dist}",
            "rpm_last_version": "0.2.4+git%{date}.%{commit}"
        },
        "110": {
            "git_branch": "master",
            "git_commit": "HEAD",
            "git_last_commit": "6ef09f29d4665d97ebc66422727af8a68394595d",
            "git_last_date": "171118.235023",
            "name": "cerbere",
            "package_name": "cerbere",
            "package_version": "0.2.2.99",
            "rpm_last_release": "2%{?dist}",
            "rpm_last_version": "0.2.2.99+git%{date}.%{commit}"
        },
        "111": {
            "git_branch": "master",
            "git_commit": "HEAD",
            "git_last_commit": "1021e36ae7be5e5d14eced6222bda8809a5532b8",
            "git_last_date": "180126.160520",
            "name": "contractor",
            "package_name": "contractor",
            "package_version": "0.3.2.99",
            "rpm_last_release": "1%{?dist}",
            "rpm_last_version": "0.3.2.99+git%{date}.%{commit}"
        },
        "112": {
            "git_branch": "master",
            "git_commit": "HEAD",
            "git_last_commit": "650426e1420cc60da0c354755f12203102b952a6",
            "git_last_date": "180210.174951",
            "name": "maya-calendar",
            "package_name": "maya-calendar",
            "package_version": "0.4.1",
            "rpm_last_release": "1%{?dist}",
            "rpm_last_version": "0.4.1+git%{date}.%{commit}"
        },
        "115": {
            "git_branch": "master",
            "git_commit": "HEAD",
            "git_last_commit": "a22d0f311af65c80ce33ab7b78dc063504495605",
            "git_last_date": "180205.001208",
            "name": "switchboard-plug-bluetooth",
            "package_name": "switchboard-plug-bluetooth",
            "package_version": "0.1.0.99",
            "rpm_last_release": "1%{?dist}",
            "rpm_last_version": "0.1.0.99+git%{date}.%{commit}"
        },
        "116": {
            "git_branch": "master",
            "git_commit": "HEAD",
            "git_last_commit": "e541fb4547e00ba2e6e3baa1fcf35d2391c1a479",
            "git_last_date": "180211.000911",
            "name": "switchboard-plug-security-privacy",
            "package_name": "switchboard-plug-security-privacy",
            "package_version": "0.1.2.99",
            "rpm_last_release": "1%{?dist}",
            "rpm_last_version": "0.1.2.99+git%{date}.%{commit}"
        },
        "117": {
            "git_branch": "master",
            "git_commit": "HEAD",
            "git_last_commit": "f528b0424101d6835946eba97484ca54ca22aa6a",
            "git_last_date": "180205.001047",
            "name": "elementary-calculator",
            "package_name": "elementary-calculator",
            "package_version": "0.1.3",
            "rpm_last_release": "1%{?dist}",
            "rpm_last_version": "0.1.3+git%{date}.%{commit}"
        },
        "118": {
            "git_branch": "master",
            "git_commit": "HEAD",
            "git_last_commit": "e7b108ea8e290dbd06ac5f85b4236dc7e0322835",
            "git_last_date": "180210.173952",
            "name": "elementary-files",
            "package_name": "elementary-files",
            "package_version": "0.3.5",
            "rpm_last_release": "1%{?dist}",
            "rpm_last_version": "0.3.5+git%{date}.%{commit}"
        },
        "119": {
            "git_branch": "master",
            "git_commit": "HEAD",
            "git_last_commit": "06a140ea84bb34cac7a433b4c3d6d193c97314e2",
            "git_last_date": "180211.000838",
            "name": "elementary-photos",
            "package_name": "elementary-photos",
            "package_version": "0.2.4",
            "rpm_last_release": "1%{?dist}",
            "rpm_last_version": "0.2.4+git%{date}.%{commit}"
        },
        "120": {
            "git_branch": "master",
            "git_commit": "HEAD",
            "git_last_commit": "6107e80686f257b1c63df7c04039d06488ca00c3",
            "git_last_date": "180211.000933",
            "name": "elementary-terminal",
            "package_name": "elementary-terminal",
            "package_version": "0.4.3",
            "rpm_last_release": "1%{?dist}",
            "rpm_last_version": "0.4.3+git%{date}.%{commit}"
        },
        "121": {
            "git_branch": "master",
            "git_commit": "HEAD",
            "git_last_commit": "0954ba6df49664c748f85e92021ba6ea57892e0a",
            "git_last_date": "180212.160234",
            "name": "elementary-code",
            "package_name": "elementary-code",
            "package_version": "2.4.1",
            "rpm_last_release": "1%{?dist}",
            "rpm_last_version": "2.4.1+git%{date}.%{commit}"
        },
        "122": {
            "git_branch": "master",
            "git_commit": "HEAD",
            "git_last_commit": "a90b1b63ca0fd2135450e00419e99f4587d9bebc",
            "git_last_date": "180209.001008",
            "name": "elementary-screenshot-tool",
            "package_name": "elementary-screenshot-tool",
            "package_version": "0.1.4",
            "rpm_last_release": "1%{?dist}",
            "rpm_last_version": "0.1.4+git%{date}.%{commit}"
        },
        "123": {
            "git_branch": "master",
            "git_commit": "HEAD",
            "git_last_commit": "946ff0b48ba87b70dde00a917fa48bf73ab4b5ce",
            "git_last_date": "180211.001114",
            "name": "wingpanel-indicator-nightlight",
            "package_name": "wingpanel-indicator-nightlight",
            "package_version": "0",
            "rpm_last_release": "1%{?dist}",
            "rpm_last_version": "0+git%{date}.%{commit}"
        },
        "124": {
            "git_branch": "master",
            "git_commit": "HEAD",
            "git_last_commit": "a71606ed2b4b261131d69c2e88cd384ef9d0b339",
            "git_last_date": "180211.072649",
            "name": "elementary-music",
            "package_name": "elementary-music",
            "package_version": "0.4.2",
            "rpm_last_release": "1%{?dist}",
            "rpm_last_version": "0.4.2+git%{date}.%{commit}"
        }
    }
}